pixies/Pixies.py
pixies/__init__.py
pixies/helper/PageTool.py
pixies/helper/__init__.py
pixies/helper/log.py
pixies/species/Clicker.py
pixies/species/Resizer.py
pixies/species/Scroller.py
pixies/species/Toucher.py
pixies/species/Typer.py
pixies/species/__init__.py
species/Clicker.py
species/Resizer.py
species/Scroller.py
species/Toucher.py
species/Typer.py
species/__init__.py
pixies-1.0.3.dist-info/LICENCE
pixies-1.0.3.dist-info/METADATA
pixies-1.0.3.dist-info/WHEEL
pixies-1.0.3.dist-info/top_level.txt
pixies-1.0.3.dist-info/RECORD
