Metadata-Version: 2.1
Name: pixies
Version: 1.0.3
Summary: A front-end monkey testing tool
Home-page: https://github.com/shanqiaosong/pixies
Author: qiaosong
Author-email: shanzh@pku.edu.cn
License: UNKNOWN
Project-URL: Bug Tracker, https://github.com/shanqiaosong/pixies/issues
Platform: UNKNOWN
Classifier: Programming Language :: Python :: 3
Classifier: License :: OSI Approved :: MIT License
Classifier: Operating System :: OS Independent
Requires-Python: >=3.6
License-File: LICENCE
Requires-Dist: selenium
